docs/__init__.py
docs/source/conf.py
docs/source/examples/quick_one.py
oceanbolt/com/congestion_client_v3/__init__.py
oceanbolt/com/congestion_client_v3/gapic_version.py
oceanbolt/com/congestion_client_v3/py.typed
oceanbolt/com/congestion_v3/__init__.py
oceanbolt/com/congestion_v3/gapic_version.py
oceanbolt/com/congestion_v3/py.typed
oceanbolt/com/congestion_v3/services/__init__.py
oceanbolt/com/congestion_v3/services/congestion_service/__init__.py
oceanbolt/com/congestion_v3/services/congestion_service/async_client.py
oceanbolt/com/congestion_v3/services/congestion_service/client.py
oceanbolt/com/congestion_v3/services/congestion_service/transports/__init__.py
oceanbolt/com/congestion_v3/services/congestion_service/transports/base.py
oceanbolt/com/congestion_v3/services/congestion_service/transports/grpc.py
oceanbolt/com/congestion_v3/services/congestion_service/transports/grpc_asyncio.py
oceanbolt/com/congestion_v3/types/__init__.py
oceanbolt/com/congestion_v3/types/service.py
oceanbolt/com/custompolygon_client_v3/__init__.py
oceanbolt/com/custompolygon_client_v3/gapic_version.py
oceanbolt/com/custompolygon_client_v3/py.typed
oceanbolt/com/custompolygon_v3/__init__.py
oceanbolt/com/custompolygon_v3/gapic_version.py
oceanbolt/com/custompolygon_v3/py.typed
oceanbolt/com/custompolygon_v3/services/__init__.py
oceanbolt/com/custompolygon_v3/services/custom_polygon_service/__init__.py
oceanbolt/com/custompolygon_v3/services/custom_polygon_service/async_client.py
oceanbolt/com/custompolygon_v3/services/custom_polygon_service/client.py
oceanbolt/com/custompolygon_v3/services/custom_polygon_service/transports/__init__.py
oceanbolt/com/custompolygon_v3/services/custom_polygon_service/transports/base.py
oceanbolt/com/custompolygon_v3/services/custom_polygon_service/transports/grpc.py
oceanbolt/com/custompolygon_v3/services/custom_polygon_service/transports/grpc_asyncio.py
oceanbolt/com/custompolygon_v3/types/__init__.py
oceanbolt/com/custompolygon_v3/types/service.py
oceanbolt.sdk-0.7.0.dist-info/LICENSE
oceanbolt.sdk-0.7.0.dist-info/METADATA
oceanbolt.sdk-0.7.0.dist-info/WHEEL
oceanbolt.sdk-0.7.0.dist-info/top_level.txt
oceanbolt.sdk-0.7.0.dist-info/RECORD
