Metadata-Version: 2.1
Name: oceanbolt.sdk
Version: 0.7.0
Summary: A Python wrapper around the Oceanbolt client API
Home-page: https://github.com/oceanbolt/oceanbolt-python-sdk
Author: Oceanbolt
Author-email: support@oceanbolt.com
License: MIT
Platform: Posix; MacOS X; Windows
Classifier: Development Status :: 3 - Alpha
Classifier: Intended Audience :: Developers
Classifier: Operating System :: OS Independent
Classifier: Programming Language :: Python :: 3.6
Classifier: Programming Language :: Python :: 3.7
Classifier: Programming Language :: Python :: 3.8
Classifier: Topic :: Internet
Classifier: Topic :: Software Development :: Libraries :: Python Modules
Requires-Python: >=3.7
License-File: LICENSE
Requires-Dist: google-api-core <3.0.0dev,>=2.11.0
Requires-Dist: libcst >=0.4.9
Requires-Dist: googleapis-common-protos <2.0.0dev,>=1.58.0
Requires-Dist: proto-plus >=1.22
Requires-Dist: grpcio >=1.51.0
Requires-Dist: pandas >=1.4.3
Requires-Dist: numpy >=1.23.2
Requires-Dist: protobuf >=3.20.3
Provides-Extra: docs
Requires-Dist: Sphinx ==5.3.0 ; extra == 'docs'
Requires-Dist: sphinx-rtd-theme ==1.1.0 ; extra == 'docs'
Requires-Dist: sphinx-autodoc-typehints ==1.19.5 ; extra == 'docs'
Provides-Extra: publish
Requires-Dist: build ==0.7.0 ; extra == 'publish'
Requires-Dist: twine ==3.6.0 ; extra == 'publish'
Provides-Extra: test
Requires-Dist: black ==21.10b0 ; extra == 'test'
Requires-Dist: mypy-extensions ==0.4.3 ; extra == 'test'
Requires-Dist: mypy ==0.910 ; extra == 'test'
Requires-Dist: pre-commit ==2.15.0 ; extra == 'test'
Requires-Dist: pytest ==6.2.5 ; extra == 'test'
Requires-Dist: pytest-dotenv ==0.5.2 ; extra == 'test'
Requires-Dist: python-dateutil ==2.8.2 ; extra == 'test'
Requires-Dist: pytest-rerunfailures ==10.2 ; extra == 'test'
Requires-Dist: mock ==4.0.3 ; extra == 'test'
Requires-Dist: flake8 ==4.0.1 ; extra == 'test'
Requires-Dist: hypothesis ==6.24.2 ; extra == 'test'
